CHANGES.txt
README.txt
TODO.txt
setup.py
plone/__init__.py
plone.phonehome.egg-info/PKG-INFO
plone.phonehome.egg-info/SOURCES.txt
plone.phonehome.egg-info/dependency_links.txt
plone.phonehome.egg-info/entry_points.txt
plone.phonehome.egg-info/namespace_packages.txt
plone.phonehome.egg-info/not-zip-safe
plone.phonehome.egg-info/requires.txt
plone.phonehome.egg-info/top_level.txt
plone/phonehome/__init__.py
plone/phonehome/checker.py
plone/phonehome/config.py
plone/phonehome/configure.zcml