Metadata-Version: 1.0
Name: plone.phonehome
Version: 1.0a3
Summary: Provide anonymous package usage statistics to the Plone Foundation
Home-page: http://plone.org
Author: Plone Foundation
Author-email: plone-developers@lists.sourceforge.net
License: GPL version 2
Platform: UNKNOWN
Classifier: Environment :: Web Environment
Classifier: Framework :: Plone
Classifier: Framework :: Zope2
Classifier: License :: OSI Approved :: GNU General Public License (GPL)
Classifier: Operating System :: OS Independent
Classifier: Programming Language :: Python
